{
	"animations": [
		{
			"loop": true,
			"offsets": [
				0,
				0
			],
			"anim": "idle",
			"fps": 12,
			"name": "narrator redesign idle",
			"indices": []
		},
		{
			"loop": false,
			"offsets": [
				-61,
				-2
			],
			"anim": "singLEFT",
			"fps": 12,
			"name": "narrator redesign left",
			"indices": []
		},
		{
			"loop": false,
			"offsets": [
				10,
				-20
			],
			"anim": "singDOWN",
			"fps": 12,
			"name": "narrator redesign down",
			"indices": []
		},
		{
			"loop": false,
			"offsets": [
				-70,
				28
			],
			"anim": "singUP",
			"fps": 12,
			"name": "narrator redesign up",
			"indices": []
		},
		{
			"loop": false,
			"offsets": [
				-23,
				0
			],
			"anim": "singRIGHT",
			"fps": 12,
			"name": "narrator redesign right",
			"indices": []
		}
	],
	"no_antialiasing": false,
	"image": "characters/narrator_redesign",
	"position": [
		0,
		200
	],
	"healthicon": "narrator-redesign",
	"flip_x": false,
	"healthbar_colors": [
		161,
		161,
		161
	],
	"camera_position": [
		0,
		-40
	],
	"sing_duration": 6.1,
	"scale": 1.2
}